markdown_live/__init__.py
markdown_live/__main__.py
markdown_live/favicon.ico
markdown_live/markdown.css
markdown_live/server.py
markdown_live-1.1.0.dist-info/LICENSE
markdown_live-1.1.0.dist-info/METADATA
markdown_live-1.1.0.dist-info/WHEEL
markdown_live-1.1.0.dist-info/entry_points.txt
markdown_live-1.1.0.dist-info/top_level.txt
markdown_live-1.1.0.dist-info/RECORD
