Metadata-Version: 2.1
Name: markdown-live
Version: 1.1.0
Summary: Serve your markdown files from an http server to see them render as you edit.
Home-page: https://github.com/rgeoghegan/markdown-live
Author: Rory Geoghegan
Author-email: r.geoghegan@gmail.com
License: BSD
Keywords: markdown
Platform: UNKNOWN
Classifier: Topic :: Utilities
Classifier: License :: OSI Approved :: BSD License
Requires-Dist: markdown (>=2.6)
